LICENSE
MANIFEST.in
README.md
requirements.txt
setup.cfg
setup.py
ibm_cloud_cis_services/__init__.py
ibm_cloud_cis_services/caching_api_v1.py
ibm_cloud_cis_services/cis_ip_api_v1.py
ibm_cloud_cis_services/common.py
ibm_cloud_cis_services/custom_pages_v1.py
ibm_cloud_cis_services/dns_record_bulk_v1.py
ibm_cloud_cis_services/dns_records_v1.py
ibm_cloud_cis_services/firewall_access_rules_v1.py
ibm_cloud_cis_services/firewall_api_v1.py
ibm_cloud_cis_services/global_load_balancer_events_v1.py
ibm_cloud_cis_services/global_load_balancer_monitor_v1.py
ibm_cloud_cis_services/global_load_balancer_pools_v0.py
ibm_cloud_cis_services/global_load_balancer_v1.py
ibm_cloud_cis_services/metrics_api_v1.py
ibm_cloud_cis_services/page_rule_api_v1.py
ibm_cloud_cis_services/range_applications_v1.py
ibm_cloud_cis_services/routing_v1.py
ibm_cloud_cis_services/security_events_api_v1.py
ibm_cloud_cis_services/ssl_certificate_api_v1.py
ibm_cloud_cis_services/user_agent_blocking_rules_v1.py
ibm_cloud_cis_services/version.py
ibm_cloud_cis_services/waf_api_v1.py
ibm_cloud_cis_services/waf_rule_groups_api_v1.py
ibm_cloud_cis_services/waf_rule_packages_api_v1.py
ibm_cloud_cis_services/waf_rules_api_v1.py
ibm_cloud_cis_services/zone_firewall_access_rules_v1.py
ibm_cloud_cis_services/zone_lockdown_v1.py
ibm_cloud_cis_services/zone_rate_limits_v1.py
ibm_cloud_cis_services/zones_settings_v1.py
ibm_cloud_cis_services/zones_v1.py
ibm_cloud_cis_services.egg-info/PKG-INFO
ibm_cloud_cis_services.egg-info/SOURCES.txt
ibm_cloud_cis_services.egg-info/dependency_links.txt
ibm_cloud_cis_services.egg-info/requires.txt
ibm_cloud_cis_services.egg-info/top_level.txt
ibm_cloud_cis_services.egg-info/zip-safe