Metadata-Version: 1.1
Name: ibm-cloud-cis-services
Version: 0.0.0
Summary: cis client library
Home-page: https://github.com/IBM/cis-python-sdk
Author: IBM
Author-email: author_email@us.ibm.com
License: Apache 2.0
Keywords: ibm_cloud_cis_services
Platform: UNKNOWN
Classifier: Programming Language :: Python
Classifier: Programming Language :: Python :: 3
Classifier: Programming Language :: Python :: 3.5
Classifier: Programming Language :: Python :: 3.6
Classifier: Programming Language :: Python :: 3.7
Classifier: Programming Language :: Python :: 3.8
Classifier: Development Status :: 4 - Beta
Classifier: Intended Audience :: Developers
Classifier: License :: OSI Approved :: Apache Software License
Classifier: Operating System :: OS Independent
Classifier: Topic :: Software Development :: Libraries :: Python Modules
Classifier: Topic :: Software Development :: Libraries :: Application Frameworks
